skybrush_ext_rc_gamepad/__init__.py
skybrush_ext_rc_gamepad/connection.py
skybrush_ext_rc_gamepad/devices.py
skybrush_ext_rc_gamepad/extension.py
skybrush_ext_rc_gamepad/hid_test.py
skybrush_ext_rc_gamepad/scanner.py
skybrush_ext_rc_gamepad/supported_devices.json
skybrush_ext_rc_gamepad/utils.py
skybrush_ext_rc_gamepad/version.py
skybrush_ext_rc_gamepad-0.6.0.dist-info/LICENSE.txt
skybrush_ext_rc_gamepad-0.6.0.dist-info/METADATA
skybrush_ext_rc_gamepad-0.6.0.dist-info/WHEEL
skybrush_ext_rc_gamepad-0.6.0.dist-info/entry_points.txt
skybrush_ext_rc_gamepad-0.6.0.dist-info/RECORD
